gobgp_client/__init__.py
gobgp_client/attribute_pb2.py
gobgp_client/capability_pb2.py
gobgp_client/client.py
gobgp_client/exceptions.py
gobgp_client/gobgp_pb2.py
gobgp_client/gobgp_pb2_grpc.py
gobgp_client-0.0.3.dist-info/LICENSE
gobgp_client-0.0.3.dist-info/METADATA
gobgp_client-0.0.3.dist-info/WHEEL
gobgp_client-0.0.3.dist-info/top_level.txt
gobgp_client-0.0.3.dist-info/RECORD
